aze/__init__.py
aze/arm_api.py
aze/az_brute_add_app_secret.py
aze/az_brute_blob_containers.py
aze/az_brute_passwords.py
aze/az_brute_service_subdomains.py
aze/az_brute_usernames.py
aze/az_download_blob.py
aze/az_download_deployment_template.py
aze/az_get_login_info.py
aze/az_get_tenant_domains.py
aze/az_get_tenant_id.py
aze/az_inspect_token.py
aze/az_list_administrative_unit_members.py
aze/az_list_administrative_unit_role_members.py
aze/az_list_blobs.py
aze/az_list_role_assignment.py
aze/az_list_sp_app_role_assignment.py
aze/az_list_user_memberof.py
aze/az_list_vm_extensions.py
aze/az_list_vm_permissions.py
aze/az_login_with_token.py
aze/az_search_token_in_cache.py
aze/az_show_ad_role.py
aze/az_show_administrative_unit.py
aze/az_whoami.py
aze/error.py
aze/graph_api.py
aze/permutations.py
aze/profile.py
aze/read_in.py
aze/request_az.py
aze/storage_api.py
aze/tenant.py
aze/tokens.py
aze/utils.py
aze/version.py
zer1t0_aze-0.0.10.dist-info/LICENSE
zer1t0_aze-0.0.10.dist-info/METADATA
zer1t0_aze-0.0.10.dist-info/WHEEL
zer1t0_aze-0.0.10.dist-info/entry_points.txt
zer1t0_aze-0.0.10.dist-info/top_level.txt
zer1t0_aze-0.0.10.dist-info/RECORD
