Metadata-Version: 2.1
Name: zer1t0-aze
Version: 0.0.10
Summary: Enhance azure cli
Home-page: https://gitlab.com/Zer1t0/aze
Author: Eloy Pérez González
Classifier: Programming Language :: Python :: 3
Classifier: License :: OSI Approved :: GNU General Public License v3 (GPLv3)
License-File: LICENSE
Requires-Dist: requests
Requires-Dist: msal-extensions
Requires-Dist: dnspython
